docfx_yaml/__init__.py
docfx_yaml/directives.py
docfx_yaml/extension.py
docfx_yaml/extract_nodes.py
docfx_yaml/markdown_utils.py
docfx_yaml/monkeypatch.py
docfx_yaml/nodes.py
docfx_yaml/settings.py
docfx_yaml/utils.py
docfx_yaml/writer.py
gcp_sphinx_docfx_yaml-3.2.4.dist-info/licenses/LICENSE
gcp_sphinx_docfx_yaml-3.2.4.dist-info/METADATA
gcp_sphinx_docfx_yaml-3.2.4.dist-info/WHEEL
gcp_sphinx_docfx_yaml-3.2.4.dist-info/top_level.txt
gcp_sphinx_docfx_yaml-3.2.4.dist-info/RECORD
