Metadata-Version: 2.4
Name: gcp-sphinx-docfx-yaml
Version: 3.2.4
Summary: Sphinx Python Domain to DocFX YAML Generator
Home-page: https://github.com/googleapis/sphinx-docfx-yaml
Author: Google LLC
Author-email: dandhlee@google.com
License: Apache 2.0
Requires-Python: >=3.10
License-File: LICENSE
Requires-Dist: black
Requires-Dist: gcp-docuploader
Requires-Dist: PyYAML
Requires-Dist: recommonmark
Requires-Dist: sphinxcontrib-applehelp==1.0.4
Requires-Dist: sphinxcontrib-devhelp==1.0.2
Requires-Dist: sphinxcontrib-htmlhelp==2.0.1
Requires-Dist: sphinxcontrib-qthelp==1.0.3
Requires-Dist: sphinxcontrib-serializinghtml==1.1.5
Requires-Dist: sphinx==4.5.0
Requires-Dist: sphinx-markdown-builder==0.5.5
Requires-Dist: sphinxcontrib.napoleon
Requires-Dist: unidecode
Requires-Dist: wheel>=0.24.0
Dynamic: author
Dynamic: author-email
Dynamic: home-page
Dynamic: license
Dynamic: license-file
Dynamic: requires-dist
Dynamic: requires-python
Dynamic: summary
